data/__init__.py
data/relations.json
data/tags_3level.json
data/tags_4level.json
data/wordsAttr.json
other/Word.py
other/__init__.py
other/readWrite.py
other/sim_sentence.py
value_tagrec/__init__.py
value_tagrec/main.py
value_tagrec/sim.py
value_tagrec-1.5.dist-info/LICENSE
value_tagrec-1.5.dist-info/METADATA
value_tagrec-1.5.dist-info/WHEEL
value_tagrec-1.5.dist-info/top_level.txt
value_tagrec-1.5.dist-info/RECORD
